marvelio/__init__.py
marvelio/_version.py
marvelio/hello.py
marvelio-0.1.0.dist-info/METADATA
marvelio-0.1.0.dist-info/WHEEL
marvelio-0.1.0.dist-info/entry_points.txt
marvelio-0.1.0.dist-info/top_level.txt
marvelio-0.1.0.dist-info/RECORD
