Metadata-Version: 2.4
Name: marvelio
Version: 0.1.0
Summary: A fully-typed Python client for the Marvel Comics API.
Author: Jeff Granof
License: MIT
Project-URL: Homepage, https://github.com/jeffgranof/marvelio
Project-URL: Documentation, https://marvelio.readthedocs.io/
Project-URL: Issue Tracker, https://github.com/jeffgranof/marvelio/issues
Requires-Python: >=3.11
Requires-Dist: httpx>=0.23.0
Requires-Dist: pydantic>=1.10.0
Requires-Dist: typing-extensions>=4.9.0
Requires-Dist: click>=8.1.0
Provides-Extra: dev
Requires-Dist: pytest; extra == "dev"
Requires-Dist: pytest-asyncio; extra == "dev"
Requires-Dist: respx; extra == "dev"
Requires-Dist: ruff; extra == "dev"
Requires-Dist: mypy; extra == "dev"
Requires-Dist: pre-commit; extra == "dev"
Requires-Dist: mkdocs-material; extra == "dev"
Provides-Extra: test
Requires-Dist: pytest; extra == "test"
Requires-Dist: pytest-asyncio; extra == "test"
Requires-Dist: respx; extra == "test"
